{
  "products": [
    {
      "name": "First product",
      "date": "2020-12-12T19:16:01.000Z",
      "place": "fridge",
      "id": "001c9b6d-00a9-465c-a2d3-afb7176a0a87"
    },
    {
      "name": "Second product",
      "date": "2020-09-29T13:45:18.000Z",
      "place": "fridge",
      "id": "001c9b7d-00a9-565c-a2d3-afb7176a0a89"
    },
    {
      "name": "Third product",
      "date": "2020-05-19T18:04:00.000Z",
      "place": "freezer",
      "id": "085fbfb7-6d84-4b16-a8cf-02e3d9b19c9a"
    }
  ]
}